[{"n":"Istanbul","c":"TR","lat":41.0138,"lon":28.9497},{"n":"Moscow","c":"RU","lat":55.752,"lon":37.6178},{"n":"Cairo","c":"EG","lat":30.0626,"lon":31.2497},{"n":"London","c":"GB","lat":51.5085,"lon":-0.1257},{"n":"Baghdad","c":"IQ","lat":33.3406,"lon":44.4009},{"n":"Saint Petersburg","c":"RU","lat":59.9386,"lon":30.3141},{"n":"Alexandria","c":"EG","lat":31.2018,"lon":29.9158},{"n":"Jeddah","c":"SA","lat":21.4901,"lon":39.1862},{"n":"Giza","c":"EG","lat":30.0094,"lon":31.2086},{"n":"Casablanca","c":"MA","lat":33.5883,"lon":-7.6114},{"n":"Ankara","c":"TR","lat":39.9199,"lon":32.8543},{"n":"Berlin","c":"DE","lat":52.5244,"lon":13.4105},{"n":"Madrid","c":"ES","lat":40.4165,"lon":-3.7026},{"n":"Bursa","c":"TR","lat":40.1956,"lon":29.0601},{"n":"Kyiv","c":"UA","lat":50.4547,"lon":30.5238},{"n":"İzmir","c":"TR","lat":38.4127,"lon":27.1384},{"n":"Algiers","c":"DZ","lat":36.7323,"lon":3.0875},{"n":"Rome","c":"IT","lat":41.8919,"lon":12.5113},{"n":"Gaziantep","c":"TR","lat":37.0594,"lon":37.3825},{"n":"Paris","c":"FR","lat":48.8534,"lon":2.3488},{"n":"Aleppo","c":"SY","lat":36.2012,"lon":37.1612},{"n":"Al Mawşil al Jadīdah","c":"IQ","lat":36.3327,"lon":43.1056},{"n":"Hamburg","c":"DE","lat":53.5507,"lon":9.993},{"n":"Beirut","c":"LB","lat":33.8933,"lon":35.5016},{"n":"Bucharest","c":"RO","lat":44.4323,"lon":26.1063},{"n":"Diyarbakır","c":"TR","lat":37.9136,"lon":40.2172},{"n":"Adana","c":"TR","lat":36.9862,"lon":35.3253},{"n":"Minsk","c":"BY","lat":53.9002,"lon":27.5665},{"n":"Budapest","c":"HU","lat":47.4984,"lon":19.0404},{"n":"Warsaw","c":"PL","lat":52.2298,"lon":21.0118},{"n":"Vienna","c":"AT","lat":48.2085,"lon":16.3721},{"n":"Barcelona","c":"ES","lat":41.3888,"lon":2.159},{"n":"Mosul","c":"IQ","lat":36.335,"lon":43.1189},{"n":"Rabat","c":"MA","lat":34.0132,"lon":-6.8326},{"n":"Erbil","c":"IQ","lat":36.1912,"lon":44.0094},{"n":"Makkah","c":"SA","lat":21.4266,"lon":39.8256},{"n":"Damascus","c":"SY","lat":33.5102,"lon":36.2913},{"n":"Stockholm","c":"SE","lat":59.3294,"lon":18.0687},{"n":"Munich","c":"DE","lat":48.1374,"lon":11.5755},{"n":"Kayseri","c":"TR","lat":38.7322,"lon":35.4853},{"n":"Konya","c":"TR","lat":37.8713,"lon":32.4846},{"n":"Kharkiv","c":"UA","lat":49.9818,"lon":36.2548},{"n":"Milan","c":"IT","lat":45.4643,"lon":9.1895},{"n":"Antalya","c":"TR","lat":36.9081,"lon":30.6956},{"n":"Tripoli","c":"LY","lat":32.8874,"lon":13.1873},{"n":"Madinah","c":"SA","lat":24.4686,"lon":39.6142},{"n":"Amman","c":"JO","lat":31.9552,"lon":35.945},{"n":"Belgrade","c":"RS","lat":44.804,"lon":20.4651},{"n":"Nizhniy Novgorod","c":"RU","lat":56.3287,"lon":44.002},{"n":"Ra’s Bayrūt","c":"LB","lat":33.9,"lon":35.4833},{"n":"Shubrā al Khaymah","c":"EG","lat":30.1251,"lon":31.2505},{"n":"Karbala","c":"IQ","lat":32.616,"lon":44.0249},{"n":"Sadr City","c":"IQ","lat":33.3889,"lon":44.4583},{"n":"Fes","c":"MA","lat":34.0331,"lon":-5.0003},{"n":"Prague","c":"CZ","lat":50.088,"lon":14.4208},{"n":"Birmingham","c":"GB","lat":52.4814,"lon":-1.8998},{"n":"Copenhagen","c":"DK","lat":55.6759,"lon":12.5655},{"n":"Sofia","c":"BG","lat":42.6975,"lon":23.3241},{"n":"Yerevan","c":"AM","lat":40.1776,"lon":44.5126},{"n":"Rostov-on-Don","c":"RU","lat":47.22,"lon":39.7077},{"n":"Oslo","c":"NO","lat":59.9127,"lon":10.7461},{"n":"Tbilisi","c":"GE","lat":41.6914,"lon":44.8341},{"n":"Voronezh","c":"RU","lat":51.6683,"lon":39.192},{"n":"Tangier","c":"MA","lat":35.7673,"lon":-5.7998},{"n":"Kirkuk","c":"IQ","lat":35.4681,"lon":44.3922},{"n":"Köln","c":"DE","lat":50.9333,"lon":6.95},{"n":"Dublin","c":"IE","lat":53.3331,"lon":-6.2489},{"n":"Brussels","c":"BE","lat":50.8505,"lon":4.3488},{"n":"Volgograd","c":"RU","lat":48.7138,"lon":44.4976},{"n":"Odesa","c":"UA","lat":46.4857,"lon":30.7438},{"n":"Pest","c":"HU","lat":47.5,"lon":19.0833},{"n":"Marrakesh","c":"MA","lat":31.6342,"lon":-7.9999},{"n":"Salé","c":"MA","lat":34.0531,"lon":-6.7985},{"n":"Jerusalem","c":"IL","lat":31.769,"lon":35.2163},{"n":"Dnipro","c":"UA","lat":48.4666,"lon":35.0407},{"n":"Sulţānah","c":"SA","lat":24.4926,"lon":39.5857},{"n":"Eskişehir","c":"TR","lat":39.7767,"lon":30.5206},{"n":"Naples","c":"IT","lat":40.8522,"lon":14.2681},{"n":"Donetsk","c":"UA","lat":48.023,"lon":37.8022},{"n":"Abū Ghurayb","c":"IQ","lat":33.3056,"lon":44.1848},{"n":"Krasnodar","c":"RU","lat":45.0453,"lon":38.9818},{"n":"Marseille","c":"FR","lat":43.297,"lon":5.3811},{"n":"Rotterdam","c":"NL","lat":51.9225,"lon":4.4792},{"n":"Turin","c":"IT","lat":45.0705,"lon":7.6868},{"n":"Valencia","c":"ES","lat":39.4739,"lon":-0.3797},{"n":"Kraków","c":"PL","lat":50.0614,"lon":19.9366},{"n":"Oran","c":"DZ","lat":35.6991,"lon":-0.6359},{"n":"Zarqa","c":"JO","lat":32.0727,"lon":36.088},{"n":"Çankaya","c":"TR","lat":39.9179,"lon":32.8627},{"n":"Küçükçekmece","c":"TR","lat":40.991,"lon":28.7712},{"n":"Port Said","c":"EG","lat":31.2653,"lon":32.3019},{"n":"Homs","c":"SY","lat":34.724,"lon":36.7256},{"n":"Erzurum","c":"TR","lat":39.9086,"lon":41.2769},{"n":"Benghazi","c":"LY","lat":32.1149,"lon":20.0686},{"n":"Malatya","c":"TR","lat":38.3502,"lon":38.3167},{"n":"Bağcılar","c":"TR","lat":41.039,"lon":28.8567},{"n":"Buraydah","c":"SA","lat":26.326,"lon":43.975},{"n":"Riga","c":"LV","lat":56.946,"lon":24.1059},{"n":"Amsterdam","c":"NL","lat":52.374,"lon":4.8897},{"n":"Lviv","c":"UA","lat":49.8383,"lon":24.0232},{"n":"Zaporizhzhya","c":"UA","lat":47.8517,"lon":35.1171},{"n":"Latakia","c":"SY","lat":35.5313,"lon":35.7909},{"n":"Suez","c":"EG","lat":29.9737,"lon":32.5263},{"n":"Agadir","c":"MA","lat":30.4202,"lon":-9.5982},{"n":"Sarajevo","c":"BA","lat":43.8486,"lon":18.3564},{"n":"Tunis","c":"TN","lat":36.819,"lon":10.1658},{"n":"Ta’if","c":"SA","lat":21.2703,"lon":40.4158},{"n":"Zaragoza","c":"ES","lat":41.6561,"lon":-0.8773},{"n":"Sevilla","c":"ES","lat":37.3828,"lon":-5.9732},{"n":"Wrocław","c":"PL","lat":51.1029,"lon":17.0301},{"n":"Madīnat an Naşr","c":"EG","lat":30.0667,"lon":31.3},{"n":"Tabuk","c":"SA","lat":28.3998,"lon":36.5715},{"n":"Athens","c":"GR","lat":37.9838,"lon":23.7278},{"n":"Zagreb","c":"HR","lat":45.8144,"lon":15.978},{"n":"Helsinki","c":"FI","lat":60.1695,"lon":24.9354},{"n":"Frankfurt am Main","c":"DE","lat":50.1155,"lon":8.6842},{"n":"Palermo","c":"IT","lat":38.1166,"lon":13.3636},{"n":"Łódź","c":"PL","lat":51.7706,"lon":19.4739},{"n":"Chisinau","c":"MD","lat":47.009,"lon":28.8594},{"n":"Glasgow","c":"GB","lat":55.8651,"lon":-4.2576},{"n":"Al Mansurah","c":"EG","lat":31.0364,"lon":31.3807},{"n":"Düsseldorf","c":"DE","lat":51.2232,"lon":6.7793},{"n":"Stuttgart","c":"DE","lat":48.7823,"lon":9.177},{"n":"Yaroslavl","c":"RU","lat":57.6299,"lon":39.8737},{"n":"Gothenburg","c":"SE","lat":57.7072,"lon":11.9668},{"n":"Ha'il","c":"SA","lat":27.5219,"lon":41.6907},{"n":"Kryvyy Rih","c":"UA","lat":47.9057,"lon":33.394},{"n":"Essen","c":"DE","lat":51.4566,"lon":7.0123},{"n":"Al Maḩallah al Kubrá","c":"EG","lat":30.9706,"lon":31.1669},{"n":"Málaga","c":"ES","lat":36.7202,"lon":-4.4203},{"n":"Dortmund","c":"DE","lat":51.5149,"lon":7.466},{"n":"Genoa","c":"IT","lat":44.4048,"lon":8.9444},{"n":"Bahçelievler","c":"TR","lat":41.0023,"lon":28.8598},{"n":"Tanta","c":"EG","lat":30.7885,"lon":31.0019},{"n":"Umraniye","c":"TR","lat":41.0164,"lon":29.1248},{"n":"Irbid","c":"JO","lat":32.5556,"lon":35.85},{"n":"Manchester","c":"GB","lat":53.4809,"lon":-2.2374},{"n":"Meknes","c":"MA","lat":33.8935,"lon":-5.5473},{"n":"Dresden","c":"DE","lat":51.0509,"lon":13.7383},{"n":"Sheffield","c":"GB","lat":53.383,"lon":-1.4659},{"n":"Pristina","c":"XK","lat":42.6727,"lon":21.1669},{"n":"Sevastopol","c":"UA","lat":44.608,"lon":33.5213},{"n":"Bremen","c":"DE","lat":53.0758,"lon":8.8072},{"n":"Vilnius","c":"LT","lat":54.6892,"lon":25.2798},{"n":"Oujda","c":"MA","lat":34.6814,"lon":-1.9086},{"n":"Ryazan’","c":"RU","lat":54.627,"lon":39.7041},{"n":"Mersin","c":"TR","lat":36.812,"lon":34.6389},{"n":"Nilüfer","c":"TR","lat":40.214,"lon":28.9157},{"n":"Leeds","c":"GB","lat":53.7965,"lon":-1.5478},{"n":"Poznań","c":"PL","lat":52.4069,"lon":16.9299},{"n":"Ar Raqqah","c":"SY","lat":35.9528,"lon":39.0079},{"n":"Antwerp","c":"BE","lat":51.2205,"lon":4.4003},{"n":"Assiut","c":"EG","lat":27.181,"lon":31.1837},{"n":"Van","c":"TR","lat":38.4946,"lon":43.3832},{"n":"Üsküdar","c":"TR","lat":41.0227,"lon":29.0137},{"n":"Lyon","c":"FR","lat":45.7491,"lon":4.8479},{"n":"Esenler","c":"TR","lat":41.0435,"lon":28.8762},{"n":"Al Fayyum","c":"EG","lat":29.31,"lon":30.8418},{"n":"Lisbon","c":"PT","lat":38.7251,"lon":-9.1498},{"n":"Nuremberg","c":"DE","lat":49.4542,"lon":11.0775},{"n":"Hannover","c":"DE","lat":52.3705,"lon":9.7332},{"n":"Edinburgh","c":"GB","lat":55.9521,"lon":-3.1965},{"n":"Toulouse","c":"FR","lat":43.6043,"lon":1.4437},{"n":"Buda","c":"HU","lat":47.5,"lon":19.0333},{"n":"Lipetsk","c":"RU","lat":52.5876,"lon":39.5515},{"n":"Leipzig","c":"DE","lat":51.3396,"lon":12.3713},{"n":"Kalininskiy","c":"RU","lat":59.9967,"lon":30.3899},{"n":"Duisburg","c":"DE","lat":51.4325,"lon":6.7652},{"n":"Homyel'","c":"BY","lat":52.4345,"lon":30.9754},{"n":"Liverpool","c":"GB","lat":53.4106,"lon":-2.9779},{"n":"Al Khuşūş","c":"EG","lat":30.1529,"lon":31.315},{"n":"Gdańsk","c":"PL","lat":54.3523,"lon":18.6491},{"n":"Tula","c":"RU","lat":54.1961,"lon":37.6182},{"n":"Najaf","c":"IQ","lat":32.0259,"lon":44.3462},{"n":"Bristol","c":"GB","lat":51.4552,"lon":-2.5966},{"n":"Kaliningrad","c":"RU","lat":54.7064,"lon":20.511},{"n":"Skopje","c":"MK","lat":41.9965,"lon":21.4314},{"n":"The Hague","c":"NL","lat":52.0767,"lon":4.2986},{"n":"Murcia","c":"ES","lat":37.987,"lon":-1.13},{"n":"Kenitra","c":"MA","lat":34.261,"lon":-6.5802},{"n":"Mykolayiv","c":"UA","lat":46.9763,"lon":31.993},{"n":"Esna","c":"EG","lat":25.2934,"lon":32.554},{"n":"Ḩamāh","c":"SY","lat":35.1318,"lon":36.7578},{"n":"Ţarţūs","c":"SY","lat":34.889,"lon":35.8866},{"n":"Karabağlar","c":"TR","lat":38.382,"lon":27.132},{"n":"Al Hillah","c":"IQ","lat":32.4637,"lon":44.4196},{"n":"Batman","c":"TR","lat":37.8874,"lon":41.1322},{"n":"Muratpaşa","c":"TR","lat":36.8916,"lon":30.765},{"n":"Şanlıurfa","c":"TR","lat":37.1671,"lon":38.7939},{"n":"Kursk","c":"RU","lat":51.7269,"lon":36.1846},{"n":"Constantine","c":"DZ","lat":36.365,"lon":6.6147},{"n":"Elazığ","c":"TR","lat":38.6743,"lon":39.2232},{"n":"Palma","c":"ES","lat":39.5694,"lon":2.6502},{"n":"Sultangazi","c":"TR","lat":41.1065,"lon":28.8685},{"n":"Stavropol","c":"RU","lat":45.0344,"lon":41.9642},{"n":"Tel Aviv","c":"IL","lat":32.0809,"lon":34.7806},{"n":"Zagazig","c":"EG","lat":30.5877,"lon":31.502},{"n":"Vinnytsya","c":"UA","lat":49.2322,"lon":28.4687},{"n":"Ismailia","c":"EG","lat":30.6043,"lon":32.2722},{"n":"East Jerusalem","c":"PS","lat":31.7834,"lon":35.2339},{"n":"Bryansk","c":"RU","lat":53.271,"lon":34.3214},{"n":"Maltepe","c":"TR","lat":40.9357,"lon":29.1551},{"n":"Bratislava","c":"SK","lat":48.1482,"lon":17.1067},{"n":"Al Ḩasakah","c":"SY","lat":36.5024,"lon":40.7477},{"n":"Luxor","c":"EG","lat":25.6989,"lon":32.6421},{"n":"Tver","c":"RU","lat":56.8584,"lon":35.9006},{"n":"Tirana","c":"AL","lat":41.3274,"lon":19.8187},{"n":"Tétouan","c":"MA","lat":35.5784,"lon":-5.3684},{"n":"Zürich","c":"CH","lat":47.3667,"lon":8.55},{"n":"Wandsbek","c":"DE","lat":53.5833,"lon":10.0831},{"n":"Gaza","c":"PS","lat":31.5016,"lon":34.4667},{"n":"Kom Ombo","c":"EG","lat":24.4767,"lon":32.9463},{"n":"Saltivka","c":"UA","lat":50.0221,"lon":36.349},{"n":"Ivanovo","c":"RU","lat":56.9999,"lon":40.9726},{"n":"West Jerusalem","c":"IL","lat":31.782,"lon":35.2196},{"n":"Antakya","c":"TR","lat":36.2066,"lon":36.1572},{"n":"Luhansk","c":"UA","lat":48.5681,"lon":39.3055},{"n":"Al Hoceïma","c":"MA","lat":35.2516,"lon":-3.9372},{"n":"Szczecin","c":"PL","lat":53.4289,"lon":14.553},{"n":"Bologna","c":"IT","lat":44.4938,"lon":11.3387},{"n":"Samsun","c":"TR","lat":41.2798,"lon":36.3361},{"n":"Tallinn","c":"EE","lat":59.437,"lon":24.7535},{"n":"Bochum","c":"DE","lat":51.4817,"lon":7.2165},{"n":"Sector 3","c":"RO","lat":44.4234,"lon":26.1687},{"n":"Kahramanmaraş","c":"TR","lat":37.5847,"lon":36.9264},{"n":"Las Palmas de Gran Canaria","c":"ES","lat":28.1018,"lon":-15.4157},{"n":"Aswān","c":"EG","lat":24.0908,"lon":32.8994},{"n":"Brno","c":"CZ","lat":49.1952,"lon":16.608},{"n":"Iaşi","c":"RO","lat":47.1667,"lon":27.6},{"n":"Utrecht","c":"NL","lat":52.0908,"lon":5.1222},{"n":"Cardiff","c":"GB","lat":51.48,"lon":-3.18},{"n":"Uşak","c":"TR","lat":38.6735,"lon":29.4058},{"n":"6th of October City","c":"EG","lat":29.8167,"lon":31.05},{"n":"Leicester","c":"GB","lat":52.6386,"lon":-1.1317},{"n":"Desna","c":"UA","lat":50.5221,"lon":30.6823},{"n":"Sector 6","c":"RO","lat":44.4358,"lon":26.0165},{"n":"Florence","c":"IT","lat":43.7792,"lon":11.2463},{"n":"Bradford","c":"GB","lat":53.7939,"lon":-1.7521},{"n":"Alanya","c":"TR","lat":36.5438,"lon":31.9998},{"n":"Malmö","c":"SE","lat":55.6059,"lon":13.0007},{"n":"Ataşehir","c":"TR","lat":40.9833,"lon":29.1167},{"n":"Hrodna","c":"BY","lat":53.6758,"lon":23.8289},{"n":"Wuppertal","c":"DE","lat":51.2563,"lon":7.1482},{"n":"Vitebsk","c":"BY","lat":55.1904,"lon":30.2049},{"n":"Dniprovskyi","c":"UA","lat":50.4537,"lon":30.6015},{"n":"Vladimir","c":"RU","lat":56.1385,"lon":40.3998},{"n":"Fatih","c":"TR","lat":41.0225,"lon":28.9408},{"n":"Misratah","c":"LY","lat":32.3753,"lon":15.0925},{"n":"Mahilyow","c":"BY","lat":53.9088,"lon":30.3404},{"n":"Pravyi Bereh","c":"UA","lat":47.115,"lon":37.5852},{"n":"Tarsus","c":"TR","lat":36.9177,"lon":34.8928},{"n":"Al Maḩmūdīyah","c":"IQ","lat":33.0622,"lon":44.3656},{"n":"Arkhangel’sk","c":"RU","lat":64.5461,"lon":40.5518},{"n":"Alicante","c":"ES","lat":38.3452,"lon":-0.4815},{"n":"Belfast","c":"GB","lat":54.5968,"lon":-5.9254},{"n":"Bilbao","c":"ES","lat":43.2627,"lon":-2.9253},{"n":"Coventry","c":"GB","lat":52.4066,"lon":-1.5122},{"n":"Belgorod","c":"RU","lat":50.6034,"lon":36.5809},{"n":"Brest","c":"BY","lat":52.1089,"lon":23.7175},{"n":"Darnytsya","c":"UA","lat":50.416,"lon":30.6953},{"n":"Annaba","c":"DZ","lat":36.9,"lon":7.7667},{"n":"Nice","c":"FR","lat":43.7031,"lon":7.2661},{"n":"Temara","c":"MA","lat":33.9287,"lon":-6.9066},{"n":"Dihok","c":"IQ","lat":36.8661,"lon":42.9879},{"n":"Kaluga","c":"RU","lat":54.5306,"lon":36.27},{"n":"Karşıyaka","c":"TR","lat":38.4577,"lon":27.1142},{"n":"Ḩadā’iq al Qubbah","c":"EG","lat":30.0884,"lon":31.2835},{"n":"Makiyivka","c":"UA","lat":48.0478,"lon":37.9258},{"n":"Krasnogvargeisky","c":"RU","lat":59.9731,"lon":30.4761},{"n":"Safi","c":"MA","lat":32.2994,"lon":-9.2372},{"n":"Simferopol","c":"UA","lat":44.9572,"lon":34.1108},{"n":"Lublin","c":"PL","lat":51.2506,"lon":22.5701},{"n":"Konak","c":"TR","lat":38.4,"lon":27.1},{"n":"Bielefeld","c":"DE","lat":52.0333,"lon":8.5333},{"n":"Blida","c":"DZ","lat":36.47,"lon":2.8277},{"n":"Bonn","c":"DE","lat":50.7344,"lon":7.0955},{"n":"Bydgoszcz","c":"PL","lat":53.1235,"lon":18.0076},{"n":"Smolensk","c":"RU","lat":54.7783,"lon":32.0509},{"n":"Plovdiv","c":"BG","lat":42.1539,"lon":24.75},{"n":"Brent","c":"GB","lat":51.5531,"lon":-0.3023},{"n":"Sochi","c":"RU","lat":43.597,"lon":39.7248},{"n":"Aksaray","c":"TR","lat":38.3725,"lon":34.0254},{"n":"Córdoba","c":"ES","lat":37.8916,"lon":-4.7728},{"n":"Birkenhead","c":"GB","lat":53.3934,"lon":-3.0148},{"n":"Nantes","c":"FR","lat":47.2172,"lon":-1.5534},{"n":"Espoo","c":"FI","lat":60.2052,"lon":24.6522},{"n":"Nottingham","c":"GB","lat":52.9536,"lon":-1.1505},{"n":"Volzhsky","c":"RU","lat":48.7858,"lon":44.7797},{"n":"Islington","c":"GB","lat":51.5362,"lon":-0.103},{"n":"Al Diwaniyah","c":"IQ","lat":31.9929,"lon":44.9255},{"n":"Varna","c":"BG","lat":43.2191,"lon":27.9102},{"n":"Marne La Vallée","c":"FR","lat":48.8358,"lon":2.6424},{"n":"Damanhur","c":"EG","lat":31.0341,"lon":30.4682},{"n":"Reading","c":"GB","lat":51.4562,"lon":-0.9711},{"n":"Constanţa","c":"RO","lat":44.1807,"lon":28.6343},{"n":"Thessaloníki","c":"GR","lat":40.6407,"lon":22.9349},{"n":"Bari","c":"IT","lat":41.1207,"lon":16.8698},{"n":"Cherepovets","c":"RU","lat":59.1333,"lon":37.9},{"n":"Hamburg-Nord","c":"DE","lat":53.5894,"lon":9.984},{"n":"Şişli","c":"TR","lat":41.0605,"lon":28.9872},{"n":"Kingston upon Hull","c":"GB","lat":53.7446,"lon":-0.3352},{"n":"Preston","c":"GB","lat":53.7628,"lon":-2.7045},{"n":"Denizli","c":"TR","lat":37.7742,"lon":29.0875},{"n":"New Cairo","c":"EG","lat":30.03,"lon":31.47},{"n":"Al Qāhirah al Jadīdah","c":"EG","lat":30.0421,"lon":31.4445},{"n":"Vologda","c":"RU","lat":59.2239,"lon":39.884},{"n":"Catania","c":"IT","lat":37.4922,"lon":15.0704},{"n":"Münster","c":"DE","lat":51.9624,"lon":7.6257},{"n":"Mannheim","c":"DE","lat":49.4891,"lon":8.4669},{"n":"Vladikavkaz","c":"RU","lat":43.041,"lon":44.6699},{"n":"Damietta","c":"EG","lat":31.4165,"lon":31.8133},{"n":"Orël","c":"RU","lat":52.9688,"lon":36.0791},{"n":"Graz","c":"AT","lat":47.0673,"lon":15.442},{"n":"Rosetta","c":"EG","lat":31.3995,"lon":30.4172},{"n":"Hamburg-Mitte","c":"DE","lat":53.55,"lon":10.0167},{"n":"Augsburg","c":"DE","lat":48.3715,"lon":10.8985},{"n":"South Dublin","c":"IE","lat":53.2903,"lon":-6.3415},{"n":"Valladolid","c":"ES","lat":41.6554,"lon":-4.7235},{"n":"Swansea","c":"GB","lat":51.6208,"lon":-3.9432},{"n":"Newcastle upon Tyne","c":"GB","lat":54.9733,"lon":-1.614},{"n":"Batikent","c":"TR","lat":39.9683,"lon":32.7308},{"n":"Białystok","c":"PL","lat":53.1333,"lon":23.1643},{"n":"Murmansk","c":"RU","lat":68.9678,"lon":33.0992},{"n":"Southend-on-Sea","c":"GB","lat":51.5378,"lon":0.7143},{"n":"Bergen","c":"NO","lat":60.393,"lon":5.3242},{"n":"Tambov","c":"RU","lat":52.7363,"lon":41.441},{"n":"Vigo","c":"ES","lat":42.2328,"lon":-8.7226},{"n":"Adıyaman","c":"TR","lat":37.7644,"lon":38.2763},{"n":"Sector 2","c":"RO","lat":44.4528,"lon":26.1332},{"n":"Batna","c":"DZ","lat":35.556,"lon":6.1741},{"n":"Kaunas","c":"LT","lat":54.9016,"lon":23.9091},{"n":"Wiesbaden","c":"DE","lat":50.086,"lon":8.2444},{"n":"Sector 4","c":"RO","lat":44.3757,"lon":26.1209},{"n":"Marienthal","c":"DE","lat":53.5667,"lon":10.0833},{"n":"Katowice","c":"PL","lat":50.2597,"lon":19.0217},{"n":"Adapazarı","c":"TR","lat":40.7806,"lon":30.4033},{"n":"Sultanbeyli","c":"TR","lat":40.9607,"lon":29.2707},{"n":"Cluj-Napoca","c":"RO","lat":46.7667,"lon":23.6},{"n":"Haifa","c":"IL","lat":32.813,"lon":34.9993},{"n":"Århus","c":"DK","lat":56.1567,"lon":10.2108},{"n":"Brighton","c":"GB","lat":50.8284,"lon":-0.1395},{"n":"Karlsruhe","c":"DE","lat":49.0094,"lon":8.4044},{"n":"Minya","c":"EG","lat":28.0919,"lon":30.7581},{"n":"Chernihiv","c":"UA","lat":51.5054,"lon":31.2866},{"n":"Gebze","c":"TR","lat":40.8028,"lon":29.4307},{"n":"Zeytinburnu","c":"TR","lat":40.9944,"lon":28.9042},{"n":"Sfax","c":"TN","lat":34.7406,"lon":10.7603},{"n":"Merkezefendi","c":"TR","lat":37.8054,"lon":29.0424},{"n":"Ostrava","c":"CZ","lat":49.8347,"lon":18.282},{"n":"Poltava","c":"UA","lat":49.5892,"lon":34.5537},{"n":"Petrozavodsk","c":"RU","lat":61.7849,"lon":34.3469},{"n":"Taganrog","c":"RU","lat":47.2363,"lon":38.9053},{"n":"Kostroma","c":"RU","lat":57.7664,"lon":40.9283},{"n":"Bab Ezzouar","c":"DZ","lat":36.7261,"lon":3.1829},{"n":"Strasbourg","c":"FR","lat":48.5839,"lon":7.7455},{"n":"Khmelnytskyi","c":"UA","lat":49.4183,"lon":26.9794},{"n":"Banī Suwayf","c":"EG","lat":29.0744,"lon":31.0979},{"n":"Ljubljana","c":"SI","lat":46.0511,"lon":14.5051},{"n":"Deir ez-Zor","c":"SY","lat":35.3359,"lon":40.1408},{"n":"Gijón","c":"ES","lat":43.5357,"lon":-5.6615},{"n":"Sector 5","c":"RO","lat":44.3881,"lon":26.0714},{"n":"Derby","c":"GB","lat":52.9228,"lon":-1.4766},{"n":"Gelsenkirchen","c":"DE","lat":51.5051,"lon":7.0965},{"n":"Cherkasy","c":"UA","lat":49.4445,"lon":32.0574},{"n":"Southampton","c":"GB","lat":50.904,"lon":-1.4043},{"n":"Çorum","c":"TR","lat":40.5489,"lon":34.9533},{"n":"Eimsbüttel","c":"DE","lat":53.5742,"lon":9.9568},{"n":"Russeifa","c":"JO","lat":32.0178,"lon":36.0464},{"n":"Shibīn al Kawm","c":"EG","lat":30.5526,"lon":31.009},{"n":"Sohag","c":"EG","lat":26.557,"lon":31.6948},{"n":"Eixample","c":"ES","lat":41.389,"lon":2.1618},{"n":"Djelfa","c":"DZ","lat":34.6728,"lon":3.263},{"n":"Bordeaux","c":"FR","lat":44.8412,"lon":-0.5805},{"n":"Aachen","c":"DE","lat":50.7766,"lon":6.0834},{"n":"Gent","c":"BE","lat":51.05,"lon":3.7167},{"n":"Chernivtsi","c":"UA","lat":48.2904,"lon":25.9324},{"n":"Sivas","c":"TR","lat":39.7483,"lon":37.0161},{"n":"Wolverhampton","c":"GB","lat":52.5855,"lon":-2.123},{"n":"Mönchengladbach","c":"DE","lat":51.1854,"lon":6.4417},{"n":"Zhytomyr","c":"UA","lat":50.2623,"lon":28.6791},{"n":"Tampere","c":"FI","lat":61.4991,"lon":23.7871},{"n":"Plymouth","c":"GB","lat":50.3715,"lon":-4.143},{"n":"Rishon LeTsiyyon","c":"IL","lat":31.971,"lon":34.7894},{"n":"Stoke-on-Trent","c":"GB","lat":53.0042,"lon":-2.1854},{"n":"Verona","c":"IT","lat":45.4385,"lon":10.9938},{"n":"Gasteiz / Vitoria","c":"ES","lat":42.85,"lon":-2.6727},{"n":"L'Hospitalet de Llobregat","c":"ES","lat":41.3597,"lon":2.1003},{"n":"Gdynia","c":"PL","lat":54.5189,"lon":18.5319},{"n":"Latina","c":"ES","lat":40.389,"lon":-3.7457},{"n":"Sumy","c":"UA","lat":50.9174,"lon":34.7991},{"n":"Milton Keynes","c":"GB","lat":52.0417,"lon":-0.7558},{"n":"Carabanchel","c":"ES","lat":40.3909,"lon":-3.7242},{"n":"Petaẖ Tiqva","c":"IL","lat":32.0871,"lon":34.8875},{"n":"Braşov","c":"RO","lat":45.6486,"lon":25.6061},{"n":"Qina","c":"EG","lat":26.1642,"lon":32.7267},{"n":"Vantaa","c":"FI","lat":60.2941,"lon":25.041},{"n":"Porto","c":"PT","lat":41.1485,"lon":-8.611},{"n":"Kiel","c":"DE","lat":54.3213,"lon":10.1349},{"n":"Sétif","c":"DZ","lat":36.1911,"lon":5.4137},{"n":"Afyonkarahisar","c":"TR","lat":38.7567,"lon":30.5433},{"n":"İskenderun","c":"TR","lat":36.5872,"lon":36.1735},{"n":"Ḩayy Khildā","c":"JO","lat":31.992,"lon":35.84},{"n":"Timişoara","c":"RO","lat":45.7537,"lon":21.2257},{"n":"A Coruña","c":"ES","lat":43.3713,"lon":-8.396},{"n":"Altona","c":"DE","lat":53.55,"lon":9.9333},{"n":"Niš","c":"RS","lat":43.3247,"lon":21.9033},{"n":"Montpellier","c":"FR","lat":43.6109,"lon":3.8763},{"n":"Częstochowa","c":"PL","lat":50.7965,"lon":19.1241},{"n":"City of Westminster","c":"GB","lat":51.4975,"lon":-0.1357},{"n":"Chemnitz","c":"DE","lat":50.8357,"lon":12.9292},{"n":"Al ‘Āshir min Ramaḑān","c":"EG","lat":30.2964,"lon":31.7463},{"n":"Northampton","c":"GB","lat":52.25,"lon":-0.8833},{"n":"Groningen","c":"NL","lat":53.2192,"lon":6.5667},{"n":"Braunschweig","c":"DE","lat":52.2659,"lon":10.5267},{"n":"Magdeburg","c":"DE","lat":52.1313,"lon":11.6319},{"n":"Puente de Vallecas","c":"ES","lat":40.3935,"lon":-3.662},{"n":"Trabzon","c":"TR","lat":41.005,"lon":39.7269},{"n":"Manisa","c":"TR","lat":38.612,"lon":27.4265},{"n":"Rivne","c":"UA","lat":50.6204,"lon":26.237},{"n":"Mar’ino","c":"RU","lat":55.65,"lon":37.7167},{"n":"Novorossiysk","c":"RU","lat":44.7319,"lon":37.7618},{"n":"Sancaktepe","c":"TR","lat":41.0024,"lon":29.2319},{"n":"Vyhurivshchyna-Troyeshchyna","c":"UA","lat":50.5114,"lon":30.6025},{"n":"Khimki","c":"RU","lat":55.9001,"lon":37.4285},{"n":"Horlivka","c":"UA","lat":48.2999,"lon":38.0171},{"n":"Obolon","c":"UA","lat":50.5132,"lon":30.5055},{"n":"Nalchik","c":"RU","lat":43.4981,"lon":43.6189},{"n":"Fuencarral","c":"ES","lat":40.5,"lon":-3.6833},{"n":"Lille","c":"FR","lat":50.6339,"lon":3.0551},{"n":"Ivano-Frankivsk","c":"UA","lat":48.9231,"lon":24.7125},{"n":"Balıkesir","c":"TR","lat":39.6492,"lon":27.8861},{"n":"Krefeld","c":"DE","lat":51.3364,"lon":6.5538},{"n":"Halle (Saale)","c":"DE","lat":51.4816,"lon":11.9795},{"n":"Freiburg","c":"DE","lat":47.9959,"lon":7.8522},{"n":"Oldham","c":"GB","lat":53.5405,"lon":-2.1183},{"n":"Podgorica","c":"ME","lat":42.4412,"lon":19.2631},{"n":"Sant Martí","c":"ES","lat":41.4181,"lon":2.1993},{"n":"Eindhoven","c":"NL","lat":51.4408,"lon":5.4778},{"n":"Elche","c":"ES","lat":38.2622,"lon":-0.7011},{"n":"Craiova","c":"RO","lat":44.3167,"lon":23.8},{"n":"Granada","c":"ES","lat":37.1882,"lon":-3.6067},{"n":"Dzerzhinsk","c":"RU","lat":56.2442,"lon":43.4554},{"n":"Ḩalwān","c":"EG","lat":29.8414,"lon":31.3008},{"n":"Mariupol","c":"UA","lat":47.0951,"lon":37.5413},{"n":"Paris 15 Vaugirard","c":"FR","lat":48.8412,"lon":2.3003},{"n":"Tripoli","c":"LB","lat":34.4335,"lon":35.8441},{"n":"Ordu","c":"TR","lat":40.9778,"lon":37.8905},{"n":"Netanya","c":"IL","lat":32.3329,"lon":34.8599},{"n":"Ciudad Lineal","c":"ES","lat":40.4451,"lon":-3.6513},{"n":"Bexley","c":"GB","lat":51.4416,"lon":0.1487},{"n":"Rennes","c":"FR","lat":48.1111,"lon":-1.6743},{"n":"Mohammedia","c":"MA","lat":33.6861,"lon":-7.383},{"n":"Sosnowiec","c":"PL","lat":50.2868,"lon":19.1039},{"n":"Staryy Oskol","c":"RU","lat":51.3025,"lon":37.8461},{"n":"Neue Neustadt","c":"DE","lat":52.15,"lon":11.6333},{"n":"Kamyanske","c":"UA","lat":48.5172,"lon":34.6062},{"n":"Ashdod","c":"IL","lat":31.7921,"lon":34.6497},{"n":"Radom","c":"PL","lat":51.4025,"lon":21.1471},{"n":"Sector 1","c":"RO","lat":44.4924,"lon":26.0483},{"n":"Luton","c":"GB","lat":51.8797,"lon":-0.4175},{"n":"Ternopil","c":"UA","lat":49.554,"lon":25.5907},{"n":"Košice","c":"SK","lat":48.7144,"lon":21.258},{"n":"Kremenchuk","c":"UA","lat":49.0625,"lon":33.4048},{"n":"Cork","c":"IE","lat":51.898,"lon":-8.4706},{"n":"Ramadi","c":"IQ","lat":33.4206,"lon":43.3078},{"n":"Mainz","c":"DE","lat":49.9819,"lon":8.2801},{"n":"Velikiy Novgorod","c":"RU","lat":58.5213,"lon":31.271},{"n":"Tilburg","c":"NL","lat":51.5555,"lon":5.0913},{"n":"Sousse","c":"TN","lat":35.8254,"lon":10.637},{"n":"Shakhty","c":"RU","lat":47.7192,"lon":40.216},{"n":"Banja Luka","c":"BA","lat":44.7788,"lon":17.2063},{"n":"Fuencarral-El Pardo","c":"ES","lat":40.4984,"lon":-3.7314},{"n":"Shevchenkivskyi","c":"UA","lat":50.4641,"lon":30.4658},{"n":"Oviedo","c":"ES","lat":43.3603,"lon":-5.8448},{"n":"Messina","c":"IT","lat":38.1939,"lon":15.5526},{"n":"Kropyvnytskyi","c":"UA","lat":48.5083,"lon":32.2662},{"n":"Oberhausen","c":"DE","lat":51.4781,"lon":6.8625},{"n":"Erfurt","c":"DE","lat":50.9773,"lon":11.0354},{"n":"Terrassa","c":"ES","lat":41.5667,"lon":2.0167},{"n":"Barking","c":"GB","lat":51.5333,"lon":0.0833},{"n":"Galaţi","c":"RO","lat":45.4369,"lon":28.0503},{"n":"Badalona","c":"ES","lat":41.45,"lon":2.2474},{"n":"Mokotów","c":"PL","lat":52.1934,"lon":21.0349},{"n":"Rybinsk","c":"RU","lat":58.0456,"lon":38.8381},{"n":"Trondheim","c":"NO","lat":63.4305,"lon":10.3951},{"n":"Oulu","c":"FI","lat":65.0124,"lon":25.4682},{"n":"Vykhino-Zhulebino","c":"RU","lat":55.702,"lon":37.8118},{"n":"Lutsk","c":"UA","lat":50.7578,"lon":25.3502},{"n":"Zelenograd","c":"RU","lat":55.9825,"lon":37.1814},{"n":"Archway","c":"GB","lat":51.5673,"lon":-0.1341},{"n":"Novi Sad","c":"RS","lat":45.2517,"lon":19.8369},{"n":"Centralniy","c":"RU","lat":59.9311,"lon":30.3607},{"n":"Bnei Brak","c":"IL","lat":32.0807,"lon":34.8338},{"n":"Khouribga","c":"MA","lat":32.8811,"lon":-6.9063},{"n":"Cartagena","c":"ES","lat":37.602,"lon":-0.984},{"n":"Jerez de la Frontera","c":"ES","lat":36.6865,"lon":-6.1361},{"n":"El Jadida","c":"MA","lat":33.2568,"lon":-8.5088},{"n":"Târgu Mureş","c":"RO","lat":46.5425,"lon":24.5575},{"n":"Mallawī","c":"EG","lat":27.7326,"lon":30.8413},{"n":"Lübeck","c":"DE","lat":53.8689,"lon":10.6873},{"n":"Sabadell","c":"ES","lat":41.5433,"lon":2.1094},{"n":"Santa Cruz de Tenerife","c":"ES","lat":28.4682,"lon":-16.2546},{"n":"Esenyurt","c":"TR","lat":41.027,"lon":28.6773},{"n":"Burgas","c":"BG","lat":42.5065,"lon":27.4689},{"n":"Pskov","c":"RU","lat":57.8192,"lon":28.3318},{"n":"Beni Mellal","c":"MA","lat":32.3372,"lon":-6.3498},{"n":"Sidi Bel Abbes","c":"DZ","lat":35.1899,"lon":-0.6309},{"n":"Pamplona","c":"ES","lat":42.8169,"lon":-1.6432},{"n":"Portsmouth","c":"GB","lat":50.799,"lon":-1.0913},{"n":"Bobruysk","c":"BY","lat":53.1464,"lon":29.2055},{"n":"Bila Tserkva","c":"UA","lat":49.8004,"lon":30.1285},{"n":"Hurghada","c":"EG","lat":27.2574,"lon":33.8129},{"n":"Móstoles","c":"ES","lat":40.3223,"lon":-3.865},{"n":"Turku","c":"FI","lat":60.4515,"lon":22.2687},{"n":"Linz","c":"AT","lat":48.3064,"lon":14.2861},{"n":"Biskra","c":"DZ","lat":34.8504,"lon":5.728},{"n":"Trieste","c":"IT","lat":45.6495,"lon":13.7768},{"n":"Zliten","c":"LY","lat":32.4674,"lon":14.5687},{"n":"Padua","c":"IT","lat":45.408,"lon":11.8859},{"n":"Vasyl'evsky Ostrov","c":"RU","lat":59.9409,"lon":30.2538},{"n":"Osmaniye","c":"TR","lat":37.0742,"lon":36.2478},{"n":"Çorlu","c":"TR","lat":41.1607,"lon":27.8009},{"n":"Debrecen","c":"HU","lat":47.5317,"lon":21.6244},{"n":"Al Khums","c":"LY","lat":32.6486,"lon":14.2619},{"n":"Favoriten","c":"AT","lat":48.1612,"lon":16.3823},{"n":"Geneva","c":"CH","lat":46.2022,"lon":6.1457},{"n":"Swindon","c":"GB","lat":51.558,"lon":-1.7812},{"n":"Nicosia","c":"CY","lat":35.1728,"lon":33.354},{"n":"Brescia","c":"IT","lat":45.5356,"lon":10.2147},{"n":"Yanbu","c":"SA","lat":24.0895,"lon":38.0618},{"n":"Charleroi","c":"BE","lat":50.4114,"lon":4.4445},{"n":"Az Zāwīyah","c":"LY","lat":32.7571,"lon":12.7276},{"n":"Salé Al Jadida","c":"MA","lat":33.9972,"lon":-6.7405},{"n":"Severnyy","c":"RU","lat":55.9358,"lon":37.5489},{"n":"Rayon KTZ","c":"UA","lat":49.9435,"lon":36.3696},{"n":"Armavir","c":"RU","lat":44.9985,"lon":41.1147},{"n":"Arīsh","c":"EG","lat":31.1316,"lon":33.7984},{"n":"Dudley","c":"GB","lat":52.5,"lon":-2.0833},{"n":"Hagen","c":"DE","lat":51.3608,"lon":7.4717},{"n":"Khūy","c":"IR","lat":38.5503,"lon":44.9521},{"n":"Gliwice","c":"PL","lat":50.2976,"lon":18.6766},{"n":"Aberdeen","c":"GB","lat":57.1437,"lon":-2.0981},{"n":"Taranto","c":"IT","lat":40.4644,"lon":17.2471},{"n":"Rzeszów","c":"PL","lat":50.0413,"lon":21.999},{"n":"Rostock","c":"DE","lat":54.0887,"lon":12.1405},{"n":"Parma","c":"IT","lat":44.7993,"lon":10.3262},{"n":"Arnavutköy","c":"TR","lat":41.1835,"lon":28.7402},{"n":"Kassel","c":"DE","lat":51.3167,"lon":9.5},{"n":"Toruń","c":"PL","lat":53.0138,"lon":18.5981},{"n":"Almería","c":"ES","lat":36.8381,"lon":-2.4597},{"n":"İzmit","c":"TR","lat":40.765,"lon":29.9293},{"n":"Reims","c":"FR","lat":49.2653,"lon":4.0285},{"n":"Laayoune","c":"EH","lat":27.1418,"lon":-13.188},{"n":"H̱olon","c":"IL","lat":32.0103,"lon":34.7792},{"n":"Durrës","c":"AL","lat":41.3235,"lon":19.4547},{"n":"Liège","c":"BE","lat":50.6337,"lon":5.5675},{"n":"Prato","c":"IT","lat":43.8805,"lon":11.097},{"n":"Kafr ash Shaykh","c":"EG","lat":31.1117,"lon":30.9399},{"n":"Çiğli","c":"TR","lat":38.4965,"lon":27.0703},{"n":"Tébessa","c":"DZ","lat":35.4042,"lon":8.1242},{"n":"Severodvinsk","c":"RU","lat":64.5583,"lon":39.8297},{"n":"Düzce","c":"TR","lat":40.8389,"lon":31.1639},{"n":"Alcalá de Henares","c":"ES","lat":40.4821,"lon":-3.36},{"n":"Başakşehir","c":"TR","lat":41.106,"lon":28.791},{"n":"Braga","c":"PT","lat":41.5514,"lon":-8.4231},{"n":"Kielce","c":"PL","lat":50.8703,"lon":20.6275},{"n":"Zabrze","c":"PL","lat":50.3249,"lon":18.7858},{"n":"Fuenlabrada","c":"ES","lat":40.2842,"lon":-3.7942},{"n":"Al Fallūjah","c":"IQ","lat":33.3491,"lon":43.786},{"n":"Bytom","c":"PL","lat":50.348,"lon":18.9328},{"n":"Leganés","c":"ES","lat":40.3272,"lon":-3.7635},{"n":"Ait Melloul","c":"MA","lat":30.3416,"lon":-9.5036},{"n":"Sutton","c":"GB","lat":51.35,"lon":-0.2},{"n":"Getafe","c":"ES","lat":40.3057,"lon":-3.733},{"n":"Donaustadt","c":"AT","lat":48.2333,"lon":16.46},{"n":"Kırıkkale","c":"TR","lat":39.8453,"lon":33.5064},{"n":"Batumi","c":"GE","lat":41.6408,"lon":41.6306},{"n":"Beersheba","c":"IL","lat":31.2518,"lon":34.7913},{"n":"El Oued","c":"DZ","lat":33.3561,"lon":6.8632},{"n":"Khuraybat as Sūq","c":"JO","lat":31.8791,"lon":35.921},{"n":"Zawiya","c":"LY","lat":32.7522,"lon":12.7278},{"n":"Le Havre","c":"FR","lat":49.4935,"lon":0.1079},{"n":"Verhunskyi","c":"UA","lat":48.5857,"lon":39.3716},{"n":"Donostia / San Sebastián","c":"ES","lat":43.3128,"lon":-1.975},{"n":"Bilbeis","c":"EG","lat":30.4204,"lon":31.5622},{"n":"Paris 20 Ménilmontant","c":"FR","lat":48.8646,"lon":2.3984},{"n":"Kütahya","c":"TR","lat":39.4242,"lon":29.9833},{"n":"Potsdam","c":"DE","lat":52.3989,"lon":13.0657},{"n":"Modena","c":"IT","lat":44.6478,"lon":10.9254},{"n":"Bolu","c":"TR","lat":40.7358,"lon":31.6061},{"n":"Al Qāmishlī","c":"SY","lat":37.0521,"lon":41.2314},{"n":"Breda","c":"NL","lat":51.5866,"lon":4.776},{"n":"Cergy-Pontoise","c":"FR","lat":49.0389,"lon":2.0781},{"n":"Unaizah","c":"SA","lat":26.1,"lon":44},{"n":"St Helens","c":"GB","lat":53.45,"lon":-2.7333},{"n":"Paris 18 Buttes-Montmartre","c":"FR","lat":48.8925,"lon":2.3444},{"n":"Sants-Montjuïc","c":"ES","lat":41.3726,"lon":2.1546},{"n":"Oradea","c":"RO","lat":47.0458,"lon":21.9183},{"n":"Saarbrücken","c":"DE","lat":49.2326,"lon":7.0098},{"n":"Skikda","c":"DZ","lat":36.8762,"lon":6.9092},{"n":"Reggio Calabria","c":"IT","lat":38.1105,"lon":15.6613},{"n":"Banhā","c":"EG","lat":30.4598,"lon":31.1842},{"n":"Quarto Oggiaro","c":"IT","lat":45.5131,"lon":9.1434},{"n":"Paris 13 Gobelins","c":"FR","lat":48.8322,"lon":2.3561},{"n":"Wādī as Sīr","c":"JO","lat":31.9545,"lon":35.8183},{"n":"Odense","c":"DK","lat":55.3959,"lon":10.3883},{"n":"Ploieşti","c":"RO","lat":44.95,"lon":26.0167},{"n":"Edirne","c":"TR","lat":41.6772,"lon":26.556},{"n":"Yasenevo","c":"RU","lat":55.6069,"lon":37.5199},{"n":"Borshchahivka","c":"UA","lat":50.4316,"lon":30.3899},{"n":"Praga Południe","c":"PL","lat":52.2442,"lon":21.0855},{"n":"Desnyanskyi","c":"UA","lat":51.5063,"lon":31.3168},{"n":"Novozavodskyi","c":"UA","lat":51.4893,"lon":31.2563},{"n":"Tsentralnyi","c":"UA","lat":47.0983,"lon":37.5484},{"n":"Podolsk","c":"RU","lat":55.4242,"lon":37.5547},{"n":"Hamm","c":"DE","lat":51.6803,"lon":7.8209},{"n":"Tiaret","c":"DZ","lat":35.371,"lon":1.317},{"n":"Amadora","c":"PT","lat":38.7538,"lon":-9.2308},{"n":"Ipswich","c":"GB","lat":52.0592,"lon":1.1555},{"n":"Paris 19 Buttes-Chaumont","c":"FR","lat":48.8817,"lon":2.3822},{"n":"Chlef","c":"DZ","lat":36.1653,"lon":1.3345},{"n":"Paris 13e Arrondissement","c":"FR","lat":48.8262,"lon":2.3599},{"n":"Basel","c":"CH","lat":47.5584,"lon":7.5733},{"n":"Nijmegen","c":"NL","lat":51.8425,"lon":5.8528},{"n":"Idkū","c":"EG","lat":31.3073,"lon":30.2981},{"n":"Uppsala","c":"SE","lat":59.8588,"lon":17.6389},{"n":"Nador","c":"MA","lat":35.1681,"lon":-2.9335},{"n":"Bielsko-Biala","c":"PL","lat":49.8225,"lon":19.0469},{"n":"Marsá Maţrūḩ","c":"EG","lat":31.3529,"lon":27.2372},{"n":"Almere Stad","c":"NL","lat":52.3702,"lon":5.2141},{"n":"Burgos","c":"ES","lat":42.3411,"lon":-3.7018},{"n":"Saint-Étienne","c":"FR","lat":45.4339,"lon":4.39},{"n":"Béjaïa","c":"DZ","lat":36.7559,"lon":5.0843},{"n":"Wigan","c":"GB","lat":53.543,"lon":-2.6371},{"n":"Karaman","c":"TR","lat":37.1811,"lon":33.215},{"n":"Siverek","c":"TR","lat":37.755,"lon":39.3167},{"n":"Bayjī","c":"IQ","lat":34.9291,"lon":43.4888},{"n":"Santander","c":"ES","lat":43.4659,"lon":-3.8049},{"n":"Tlemcen","c":"DZ","lat":34.8783,"lon":-1.315},{"n":"Croydon","c":"GB","lat":51.3833,"lon":-0.1},{"n":"Khān Yūnis","c":"PS","lat":31.3402,"lon":34.3063},{"n":"Mülheim","c":"DE","lat":51.4322,"lon":6.8797},{"n":"Albacete","c":"ES","lat":38.9942,"lon":-1.8564},{"n":"Alcorcón","c":"ES","lat":40.3458,"lon":-3.8249},{"n":"Isparta","c":"TR","lat":37.7644,"lon":30.5522},{"n":"Warrington","c":"GB","lat":53.3925,"lon":-2.5802},{"n":"Klaipėda","c":"LT","lat":55.7068,"lon":21.1391},{"n":"Walsall","c":"GB","lat":52.5853,"lon":-1.984},{"n":"Herne","c":"DE","lat":51.5388,"lon":7.2257},{"n":"Lyublino","c":"RU","lat":55.6774,"lon":37.76},{"n":"Mansfield","c":"GB","lat":53.1333,"lon":-1.2},{"n":"Reggio nell'Emilia","c":"IT","lat":44.6983,"lon":10.6312},{"n":"Castelló de la Plana","c":"ES","lat":39.9857,"lon":-0.0493},{"n":"Prizren","c":"XK","lat":42.2139,"lon":20.7397},{"n":"Baranovichi","c":"BY","lat":53.1325,"lon":26.0077},{"n":"Ramat Gan","c":"IL","lat":32.0823,"lon":34.8107},{"n":"East Helsinki","c":"FI","lat":60.2104,"lon":25.0829},{"n":"Sunderland","c":"GB","lat":54.9046,"lon":-1.3822},{"n":"Ouargla","c":"DZ","lat":31.9493,"lon":5.325},{"n":"Olsztyn","c":"PL","lat":53.7838,"lon":20.4927},{"n":"Harburg","c":"DE","lat":53.4606,"lon":9.9839},{"n":"Arad","c":"RO","lat":46.1833,"lon":21.3167},{"n":"Pilsen","c":"CZ","lat":49.7475,"lon":13.3776},{"n":"Toulon","c":"FR","lat":43.1244,"lon":5.9284},{"n":"Jabālyā","c":"PS","lat":31.5272,"lon":34.4835},{"n":"Angers","c":"FR","lat":47.4716,"lon":-0.552},{"n":"Ilford","c":"GB","lat":51.5577,"lon":0.0728},{"n":"Horta-Guinardó","c":"ES","lat":41.4185,"lon":2.1677},{"n":"Pátra","c":"GR","lat":38.2462,"lon":21.7351},{"n":"Rutchenkivskyi","c":"UA","lat":47.976,"lon":37.6968},{"n":"Volgodonsk","c":"RU","lat":47.5114,"lon":42.1527},{"n":"Fortechnyi","c":"UA","lat":48.4986,"lon":32.2537},{"n":"Darmstadt","c":"DE","lat":49.8717,"lon":8.6503},{"n":"Novocherkassk","c":"RU","lat":47.4222,"lon":40.0937},{"n":"Linköping","c":"SE","lat":58.4109,"lon":15.6216},{"n":"Osnabrück","c":"DE","lat":52.2726,"lon":8.0498},{"n":"Nou Barris","c":"ES","lat":41.4416,"lon":2.1773},{"n":"Dar Bouazza","c":"MA","lat":33.5153,"lon":-7.8168},{"n":"Béchar","c":"DZ","lat":31.6167,"lon":-2.2167},{"n":"Gölbaşı","c":"TR","lat":39.7904,"lon":32.809},{"n":"Slough","c":"GB","lat":51.5095,"lon":-0.5954},{"n":"Neukölln","c":"DE","lat":52.4772,"lon":13.4313},{"n":"Zenica","c":"BA","lat":44.2017,"lon":17.904},{"n":"Solingen","c":"DE","lat":51.1734,"lon":7.0845},{"n":"Nazran","c":"RU","lat":43.226,"lon":44.7732},{"n":"Piraeus","c":"GR","lat":37.942,"lon":23.6462},{"n":"Bournemouth","c":"GB","lat":50.7205,"lon":-1.8795},{"n":"Sidon","c":"LB","lat":33.5575,"lon":35.3715},{"n":"Peterborough","c":"GB","lat":52.5736,"lon":-0.2478},{"n":"Ludwigshafen am Rhein","c":"DE","lat":49.4812,"lon":8.4464},{"n":"Büyükçekmece","c":"TR","lat":41.0207,"lon":28.585},{"n":"Aydın","c":"TR","lat":37.845,"lon":27.8396},{"n":"Mostaganem","c":"DZ","lat":35.9312,"lon":0.0892},{"n":"Floridsdorf","c":"AT","lat":48.25,"lon":16.4},{"n":"Leverkusen","c":"DE","lat":51.0303,"lon":6.9843},{"n":"Haarlem","c":"NL","lat":52.3808,"lon":4.6368},{"n":"Arnhem","c":"NL","lat":51.98,"lon":5.9111},{"n":"Taza","c":"MA","lat":34.21,"lon":-4.01},{"n":"Oxford","c":"GB","lat":51.7522,"lon":-1.256},{"n":"Al Maţarīyah","c":"EG","lat":31.1829,"lon":32.0311},{"n":"Hortaleza","c":"ES","lat":40.4744,"lon":-3.6411},{"n":"Newport","c":"GB","lat":51.5877,"lon":-2.9983},{"n":"'s-Hertogenbosch","c":"NL","lat":51.6992,"lon":5.3042},{"n":"Szeged","c":"HU","lat":46.253,"lon":20.1482},{"n":"Anderlecht","c":"BE","lat":50.8362,"lon":4.3145},{"n":"Mytishchi","c":"RU","lat":55.911,"lon":37.7296},{"n":"Hebron","c":"PS","lat":31.5294,"lon":35.0938},{"n":"Nyzhnodniprovsk","c":"UA","lat":48.4755,"lon":35.1167},{"n":"Ash Sharqāt","c":"IQ","lat":35.5172,"lon":43.2281},{"n":"Dijon","c":"FR","lat":47.3134,"lon":5.0139},{"n":"Paris 16 Passy","c":"FR","lat":48.8637,"lon":2.2769},{"n":"Oldenburg","c":"DE","lat":53.1404,"lon":8.2148},{"n":"Paris 17 Batignolles-Monceau","c":"FR","lat":48.8835,"lon":2.3219},{"n":"Khoroshëvo-Mnevniki","c":"RU","lat":55.7836,"lon":37.4714},{"n":"Bibirevo","c":"RU","lat":55.8833,"lon":37.6},{"n":"Bordj Bou Arreridj","c":"DZ","lat":36.0739,"lon":4.7614},{"n":"Grenoble","c":"FR","lat":45.1787,"lon":5.7148},{"n":"Sāmarrā’","c":"IQ","lat":34.1959,"lon":43.8857},{"n":"El Achir","c":"DZ","lat":36.0639,"lon":4.6274},{"n":"Gol’yanovo","c":"RU","lat":55.823,"lon":37.8131},{"n":"Admiralteisky","c":"RU","lat":59.923,"lon":30.3},{"n":"Avtozavodskyi","c":"UA","lat":49.0975,"lon":33.4321},{"n":"San Blas-Canillejas","c":"ES","lat":40.4389,"lon":-3.6154},{"n":"Salzburg","c":"AT","lat":47.7994,"lon":13.044},{"n":"Livorno","c":"IT","lat":43.5443,"lon":10.3262},{"n":"Tiraspol","c":"MD","lat":46.8428,"lon":29.6284},{"n":"Enfield Town","c":"GB","lat":51.6515,"lon":-0.085},{"n":"Qalyub","c":"EG","lat":30.1792,"lon":31.2056},{"n":"Marbella","c":"ES","lat":36.5154,"lon":-4.8858},{"n":"York","c":"GB","lat":53.9576,"lon":-1.0827},{"n":"Fès al Bali","c":"MA","lat":34.0701,"lon":-4.9547},{"n":"Örebro","c":"SE","lat":59.2741,"lon":15.2066},{"n":"Al Miqdādīyah","c":"IQ","lat":33.9786,"lon":44.9369},{"n":"Ar Ramthā","c":"JO","lat":32.5587,"lon":36.0082},{"n":"Zemun","c":"RS","lat":44.8458,"lon":20.4012},{"n":"Telford","c":"GB","lat":52.6766,"lon":-2.4493},{"n":"Settat","c":"MA","lat":33.001,"lon":-7.6166},{"n":"Al Ḩawāmidīyah","c":"EG","lat":29.9,"lon":31.25},{"n":"Tetuán de las Victorias","c":"ES","lat":40.4597,"lon":-3.6975},{"n":"Brăila","c":"RO","lat":45.2715,"lon":27.9743},{"n":"Lyubertsy","c":"RU","lat":55.6772,"lon":37.8932},{"n":"Miskolc","c":"HU","lat":48.1033,"lon":20.7781},{"n":"Abū Kabīr","c":"EG","lat":30.7251,"lon":31.6715},{"n":"Janzūr","c":"LY","lat":32.8187,"lon":13.0173},{"n":"Kovrov","c":"RU","lat":56.3575,"lon":41.3189},{"n":"Viranşehir","c":"TR","lat":37.2235,"lon":39.7552},{"n":"Limassol","c":"CY","lat":34.6841,"lon":33.0379},{"n":"Mīt Ghamr","c":"EG","lat":30.7152,"lon":31.2592},{"n":"Enschede","c":"NL","lat":52.2183,"lon":6.8958},{"n":"Souk Ahras","c":"DZ","lat":36.2864,"lon":7.9511},{"n":"Kreuzberg","c":"DE","lat":52.4997,"lon":13.4034},{"n":"Baqubah","c":"IQ","lat":33.754,"lon":44.6052},{"n":"Sumayl","c":"IQ","lat":36.8582,"lon":42.8482},{"n":"Simele","c":"IQ","lat":36.8583,"lon":42.8501},{"n":"Neuss","c":"DE","lat":51.1981,"lon":6.685},{"n":"Strogino","c":"RU","lat":55.8184,"lon":37.4122},{"n":"Poole","c":"GB","lat":50.7143,"lon":-1.9846},{"n":"Akhmīm","c":"EG","lat":26.5622,"lon":31.7457},{"n":"Regensburg","c":"DE","lat":49.0151,"lon":12.1016},{"n":"Girga","c":"EG","lat":26.3372,"lon":31.8929},{"n":"Logroño","c":"ES","lat":42.4661,"lon":-2.4512},{"n":"Sykhiv","c":"UA","lat":49.7943,"lon":24.0628},{"n":"Ṣuwayliḥ","c":"JO","lat":32.0221,"lon":35.8439},{"n":"Erzincan","c":"TR","lat":39.7392,"lon":39.4901},{"n":"Kırşehir","c":"TR","lat":39.1458,"lon":34.1639},{"n":"Zarichnyi","c":"UA","lat":50.9038,"lon":34.8093},{"n":"La Laguna","c":"ES","lat":28.4853,"lon":-16.3201},{"n":"Badajoz","c":"ES","lat":38.8779,"lon":-6.9706},{"n":"Malatia-Sebastia","c":"AM","lat":40.174,"lon":44.4457},{"n":"Kızıltepe","c":"TR","lat":37.1884,"lon":40.5772},{"n":"Balashikha","c":"RU","lat":55.7948,"lon":37.9479},{"n":"Zhulebino","c":"RU","lat":55.7,"lon":37.85},{"n":"Split","c":"HR","lat":43.5089,"lon":16.4392},{"n":"Ursynów","c":"PL","lat":52.1505,"lon":21.0504},{"n":"Madrid Centro","c":"ES","lat":40.4183,"lon":-3.7027},{"n":"Burnley","c":"GB","lat":53.8,"lon":-2.2333},{"n":"Reẖovot","c":"IL","lat":31.8942,"lon":34.812},{"n":"Sabha","c":"LY","lat":27.0377,"lon":14.4283},{"n":"Disūq","c":"EG","lat":31.1326,"lon":30.6478},{"n":"Cagliari","c":"IT","lat":39.2305,"lon":9.1192},{"n":"Harrow","c":"GB","lat":51.5784,"lon":-0.3321},{"n":"Berrechid","c":"MA","lat":33.2655,"lon":-7.5875},{"n":"Huddersfield","c":"GB","lat":53.649,"lon":-1.7842},{"n":"Kerch","c":"UA","lat":45.3567,"lon":36.4754},{"n":"Prenzlauer Berg","c":"DE","lat":52.5388,"lon":13.4244},{"n":"Melitopol","c":"UA","lat":46.8473,"lon":35.382},{"n":"Arganzuela","c":"ES","lat":40.4002,"lon":-3.6962},{"n":"Jyväskylä","c":"FI","lat":62.2415,"lon":25.7209},{"n":"Rimini","c":"IT","lat":44.0575,"lon":12.5653},{"n":"Stavanger","c":"NO","lat":58.9701,"lon":5.7333},{"n":"Arar","c":"SA","lat":30.9753,"lon":41.0381},{"n":"Nîmes","c":"FR","lat":43.8366,"lon":4.3579},{"n":"Dundee","c":"GB","lat":56.4691,"lon":-2.9749},{"n":"Sarrià-Sant Gervasi","c":"ES","lat":41.401,"lon":2.1394},{"n":"Clermont-Ferrand","c":"FR","lat":45.7797,"lon":3.0868},{"n":"Salamanca","c":"ES","lat":40.4297,"lon":-3.6797},{"n":"Kolomna","c":"RU","lat":55.0711,"lon":38.784},{"n":"Mestre","c":"IT","lat":45.4917,"lon":12.2454},{"n":"Shevchenko","c":"UA","lat":49.5645,"lon":34.5387},{"n":"Kuntsevo","c":"RU","lat":55.7422,"lon":37.4023}]